scrapy_scraperapi_middleware/__init__.py
scrapy_scraperapi_middleware/middleware.py
scrapy_scraperapi_middleware-1.0.dist-info/LICENSE
scrapy_scraperapi_middleware-1.0.dist-info/METADATA
scrapy_scraperapi_middleware-1.0.dist-info/WHEEL
scrapy_scraperapi_middleware-1.0.dist-info/top_level.txt
scrapy_scraperapi_middleware-1.0.dist-info/RECORD
