Metadata-Version: 2.1
Name: scrapy-scraperapi-middleware
Version: 1.0
Summary: Middleware to easily implement ScraperAPI in Scrapy projects
Home-page: UNKNOWN
Author: Patrick Klein
License: MIT
Project-URL: Source, https://github.com/patkle/scrapy-scraperapi-middleware
Keywords: scrapy middleware proxy ScraperAPI
Platform: UNKNOWN
Classifier: Intended Audience :: Developers
Classifier: License :: OSI Approved :: MIT License
Classifier: Programming Language :: Python :: 3
Classifier: Topic :: Utilities
Requires-Python: >=3
